faceshine/__init__.py
faceshine/__main__.py
faceshine/app.py
faceshine/utils.py
faceshine/tasks/__init__.py
faceshine/tasks/base/__init__.py
faceshine/tasks/base/ai_enhancer.py
faceshine/tasks/base/ai_preprocces.py
faceshine/tasks/base/ai_upsampler.py
faceshine/tasks/base/task.py
faceshine/tasks/colorizer/__init__.py
faceshine/tasks/colorizer/model_image_colorizer.py
faceshine/tasks/colorizer/task_image_colorizer.py
faceshine/tasks/faceparser/__init__.py
faceshine/tasks/faceparser/task_face_segmentation.py
faceshine/tasks/faceparser/bisnet/__init__.py
faceshine/tasks/faceparser/bisnet/model.py
faceshine/tasks/faceparser/bisnet/resnet.py
faceshine/tasks/lowlight/__init__.py
faceshine/tasks/lowlight/task_low_light.py
faceshine/tasks/lowlight/model/__init__.py
faceshine/tasks/lowlight/model/dataloader.py
faceshine/tasks/lowlight/model/model.py
faceshine/tasks/segmentation/__init__.py
faceshine/tasks/segmentation/task_zero_background.py
faceshine/tasks/superface/__init__.py
faceshine/tasks/superface/task_super_face.py
faceshine/tasks/zeroscratches/__init__.py
faceshine/tasks/zeroscratches/task_erase_scratches.py
faceshine-1.0.4.dist-info/LICENSE
faceshine-1.0.4.dist-info/METADATA
faceshine-1.0.4.dist-info/WHEEL
faceshine-1.0.4.dist-info/entry_points.txt
faceshine-1.0.4.dist-info/top_level.txt
faceshine-1.0.4.dist-info/RECORD
